sdc11073/__init__.py
sdc11073/certloader.py
sdc11073/commlog.py
sdc11073/definitions_base.py
sdc11073/definitions_sdc.py
sdc11073/etc.py
sdc11073/exceptions.py
sdc11073/intervaltimer.py
sdc11073/location.py
sdc11073/loghelper.py
sdc11073/multikey.py
sdc11073/namespaces.py
sdc11073/network.py
sdc11073/py.typed
sdc11073/schema_resolver.py
sdc11073/xml_utils.py
sdc11073/consumer/__init__.py
sdc11073/consumer/components.py
sdc11073/consumer/consumerimpl.py
sdc11073/consumer/manipulator.py
sdc11073/consumer/operations.py
sdc11073/consumer/request_handler_deferred.py
sdc11073/consumer/subscription.py
sdc11073/consumer/serviceclients/__init__.py
sdc11073/consumer/serviceclients/containmenttreeservice.py
sdc11073/consumer/serviceclients/contextservice.py
sdc11073/consumer/serviceclients/descriptioneventservice.py
sdc11073/consumer/serviceclients/getservice.py
sdc11073/consumer/serviceclients/localizationservice.py
sdc11073/consumer/serviceclients/serviceclientbase.py
sdc11073/consumer/serviceclients/setservice.py
sdc11073/consumer/serviceclients/stateeventservice.py
sdc11073/consumer/serviceclients/waveformservice.py
sdc11073/dispatch/__init__.py
sdc11073/dispatch/dispatchkey.py
sdc11073/dispatch/messageconverter.py
sdc11073/dispatch/pathelementregistry.py
sdc11073/dispatch/request.py
sdc11073/entity_mdib/__init__.py
sdc11073/entity_mdib/entities.py
sdc11073/entity_mdib/entity_consumermdib.py
sdc11073/entity_mdib/entity_consumermdibxtra.py
sdc11073/entity_mdib/entity_mdibbase.py
sdc11073/entity_mdib/entity_providermdib.py
sdc11073/entity_mdib/entity_providermdibxtra.py
sdc11073/entity_mdib/entity_transactions.py
sdc11073/httpserver/__init__.py
sdc11073/httpserver/compression.py
sdc11073/httpserver/httpreader.py
sdc11073/httpserver/httprequesthandler.py
sdc11073/httpserver/httpserverimpl.py
sdc11073/mdib/__init__.py
sdc11073/mdib/consumermdib.py
sdc11073/mdib/consumermdibxtra.py
sdc11073/mdib/containerbase.py
sdc11073/mdib/descriptorcontainers.py
sdc11073-2.3.0.dist-info/METADATA
sdc11073-2.3.0.dist-info/WHEEL
sdc11073-2.3.0.dist-info/licenses/LICENSE
sdc11073-2.3.0.dist-info/RECORD
