Metadata-Version: 2.4
Name: sdc11073
Version: 2.3.0
Summary: Pure python implementation of IEEE11073 SDC protocol
Project-URL: Homepage, https://github.com/Draegerwerk/sdc11073
Project-URL: Bug Tracker, https://github.com/Draegerwerk/sdc11073/issues
Author-email: Bernd Deichmann <bernd.deichmann@draeger.com>, Leon Budnick <leon.budnick@draeger.com>
License-File: LICENSE
Keywords: IEEE11073,SDC
Classifier: Development Status :: 5 - Production/Stable
Classifier: Intended Audience :: Developers
Classifier: License :: OSI Approved :: MIT License
Classifier: Operating System :: Microsoft :: Windows
Classifier: Operating System :: POSIX :: Linux
Classifier: Programming Language :: Python :: 3.9
Classifier: Programming Language :: Python :: 3.10
Classifier: Programming Language :: Python :: 3.11
Classifier: Programming Language :: Python :: 3.12
Classifier: Programming Language :: Python :: 3.13
Classifier: Topic :: Software Development
Requires-Python: <3.14,>=3.9
Requires-Dist: aiohttp
Requires-Dist: ifaddr
Requires-Dist: lxml<6,>=2.3
Requires-Dist: typing-extensions; python_version < '3.10'
Provides-Extra: dev
Requires-Dist: lz4; extra == 'dev'
Requires-Dist: mypy; extra == 'dev'
Requires-Dist: pytest; extra == 'dev'
Requires-Dist: pytest-cov; extra == 'dev'
Requires-Dist: pytest-html; extra == 'dev'
Requires-Dist: pytest-xdist[psutil]; extra == 'dev'
Requires-Dist: ruff>=0.9.3; extra == 'dev'
Requires-Dist: types-lxml; extra == 'dev'
Provides-Extra: lz4
Requires-Dist: lz4; extra == 'lz4'
Provides-Extra: mypy
Requires-Dist: mypy; extra == 'mypy'
Requires-Dist: types-lxml; extra == 'mypy'
Provides-Extra: test
Requires-Dist: lz4; extra == 'test'
Requires-Dist: pytest; extra == 'test'
Requires-Dist: pytest-cov; extra == 'test'
Requires-Dist: pytest-html; extra == 'test'
Requires-Dist: pytest-xdist[psutil]; extra == 'test'
